{"body":{"lts":"4.4","stable":"5.3","next":"5.4","previous":"5.2","dev":"5.4","dev-name":"5.4","splits":{"symfony\/allmysms-notifier":["5.3","5.4","6.0"],"symfony\/amazon-mailer":["4.3","4.4","5.0","5.1","5.2","5.3","5.4","6.0"],"symfony\/amazon-sqs-messenger":["5.1","5.2","5.3","5.4","6.0"],"symfony\/amqp-messenger":["5.1","5.2","5.3","5.4","6.0"],"symfony\/asset":["2.7","2.8","3.4","4.0","4.1","4.2","4.3","4.4","5.0","5.1","5.2","5.3","5.4","6.0"],"symfony\/beanstalkd-messenger":["5.2","5.3","5.4","6.0"],"symfony\/browser-kit":["2.7","2.8","3.4","4.0","4.1","4.2","4.3","4.4","5.0","5.1","5.2","5.3","5.4","6.0"],"symfony\/cache":["3.4","4.0","4.1","4.2","4.3","4.4","5.0","5.1","5.2","5.3","5.4","6.0"],"symfony\/class-loader":["2.7","2.8","3.4"],"symfony\/clickatell-notifier":["5.3","5.4","6.0"],"symfony\/config":["2.7","2.8","3.4","4.0","4.1","4.2","4.3","4.4","5.0","5.1","5.2","5.3","5.4","6.0"],"symfony\/console":["2.7","2.8","3.4","4.0","4.1","4.2","4.3","4.4","5.0","5.1","5.2","5.3","5.4","6.0"],"symfony\/contracts":["5.4"],"symfony\/crowdin-translation-provider":["5.3","5.4","6.0"],"symfony\/css-selector":["2.7","2.8","3.4","4.0","4.1","4.2","4.3","4.4","5.0","5.1","5.2","5.3","5.4","6.0"],"symfony\/debug":["2.7","2.8","3.4","4.0","4.1","4.2","4.3","4.4"],"symfony\/debug-bundle":["2.7","2.8","3.4","4.0","4.1","4.2","4.3","4.4","5.0","5.1","5.2","5.3","5.4","6.0"],"symfony\/dependency-injection":["2.7","2.8","3.4","4.0","4.1","4.2","4.3","4.4","5.0","5.1","5.2","5.3","5.4","6.0"],"symfony\/discord-notifier":["5.2","5.3","5.4","6.0"],"symfony\/doctrine-bridge":["2.7","2.8","3.4","4.0","4.1","4.2","4.3","4.4","5.0","5.1","5.2","5.3","5.4","6.0"],"symfony\/doctrine-messenger":["5.1","5.2","5.3","5.4","6.0"],"symfony\/dom-crawler":["2.7","2.8","3.4","4.0","4.1","4.2","4.3","4.4","5.0","5.1","5.2","5.3","5.4","6.0"],"symfony\/dotenv":["3.4","4.0","4.1","4.2","4.3","4.4","5.0","5.1","5.2","5.3","5.4","6.0"],"symfony\/error-handler":["4.4","5.0","5.1","5.2","5.3","5.4","6.0"],"symfony\/esendex-notifier":["5.2","5.3","5.4","6.0"],"symfony\/event-dispatcher":["2.7","2.8","3.4","4.0","4.1","4.2","4.3","4.4","5.0","5.1","5.2","5.3","5.4","6.0"],"symfony\/expression-language":["2.7","2.8","3.4","4.0","4.1","4.2","4.3","4.4","5.0","5.1","5.2","5.3","5.4","6.0"],"symfony\/fake-chat-notifier":["5.3","5.4","6.0"],"symfony\/fake-sms-notifier":["5.3","5.4","6.0"],"symfony\/filesystem":["2.7","2.8","3.4","4.0","4.1","4.2","4.3","4.4","5.0","5.1","5.2","5.3","5.4","6.0"],"symfony\/finder":["2.7","2.8","3.4","4.0","4.1","4.2","4.3","4.4","5.0","5.1","5.2","5.3","5.4","6.0"],"symfony\/firebase-notifier":["5.1","5.2","5.3","5.4","6.0"],"symfony\/form":["2.7","2.8","3.4","4.0","4.1","4.2","4.3","4.4","5.0","5.1","5.2","5.3","5.4","6.0"],"symfony\/framework-bundle":["2.7","2.8","3.4","4.0","4.1","4.2","4.3","4.4","5.0","5.1","5.2","5.3","5.4","6.0"],"symfony\/free-mobile-notifier":["5.1","5.2","5.3","5.4","6.0"],"symfony\/gatewayapi-notifier":["5.3","5.4","6.0"],"symfony\/gitter-notifier":["5.3","5.4","6.0"],"symfony\/google-chat-notifier":["5.2","5.3","5.4","6.0"],"symfony\/google-mailer":["4.3","4.4","5.0","5.1","5.2","5.3","5.4","6.0"],"symfony\/http-client":["4.3","4.4","5.0","5.1","5.2","5.3","5.4","6.0"],"symfony\/http-foundation":["2.7","2.8","3.4","4.0","4.1","4.2","4.3","4.4","5.0","5.1","5.2","5.3","5.4","6.0"],"symfony\/http-kernel":["2.7","2.8","3.4","4.0","4.1","4.2","4.3","4.4","5.0","5.1","5.2","5.3","5.4","6.0"],"symfony\/inflector":["3.4","4.0","4.1","4.2","4.3","4.4","5.0","5.1","5.2","5.3","5.4"],"symfony\/infobip-notifier":["5.2","5.3","5.4","6.0"],"symfony\/intl":["2.7","2.8","3.4","4.0","4.1","4.2","4.3","4.4","5.0","5.1","5.2","5.3","5.4","6.0"],"symfony\/iqsms-notifer":["5.3","5.4","6.0"],"symfony\/ldap":["2.8","3.4","4.0","4.1","4.2","4.3","4.4","5.0","5.1","5.2","5.3","5.4","6.0"],"symfony\/light-sms-notifier":["5.3","5.4","6.0"],"symfony\/linked-in-notifier":["5.2","5.3","5.4","6.0"],"symfony\/lock":["3.4","4.0","4.1","4.2","4.3","4.4","5.0","5.1","5.2","5.3","5.4","6.0"],"symfony\/loco-translation-provider":["5.3","5.4","6.0"],"symfony\/lokalise-translation-provider":["5.3","5.4","6.0"],"symfony\/mailchimp-mailer":["4.3","4.4","5.0","5.1","5.2","5.3","5.4","6.0"],"symfony\/mailer":["4.3","4.4","5.0","5.1","5.2","5.3","5.4","6.0"],"symfony\/mailgun-mailer":["4.3","4.4","5.0","5.1","5.2","5.3","5.4","6.0"],"symfony\/mailjet-mailer":["5.2","5.3","5.4","6.0"],"symfony\/mattermost-notifier":["5.1","5.2","5.3","5.4","6.0"],"symfony\/mercure-notifier":["5.3","5.4","6.0"],"symfony\/message-bird-notifier":["5.3","5.4","6.0"],"symfony\/messenger":["4.1","4.2","4.3","4.4","5.0","5.1","5.2","5.3","5.4","6.0"],"symfony\/microsoft-teams-notifier":["5.3","5.4","6.0"],"symfony\/mime":["4.3","4.4","5.0","5.1","5.2","5.3","5.4","6.0"],"symfony\/mobyt-notifier":["5.2","5.3","5.4","6.0"],"symfony\/monolog-bridge":["2.7","2.8","3.4","4.0","4.1","4.2","4.3","4.4","5.0","5.1","5.2","5.3","5.4","6.0"],"symfony\/nexmo-notifier":["5.0","5.1","5.2","5.3","5.4","6.0"],"symfony\/notifier":["5.0","5.1","5.2","5.3","5.4","6.0"],"symfony\/octopush-notifier":["5.3","5.4","6.0"],"symfony\/options-resolver":["2.7","2.8","3.4","4.0","4.1","4.2","4.3","4.4","5.0","5.1","5.2","5.3","5.4","6.0"],"symfony\/ovh-cloud-notifier":["5.1","5.2","5.3","5.4","6.0"],"symfony\/password-hasher":["5.3","5.4","6.0"],"symfony\/postmark-mailer":["4.3","4.4","5.0","5.1","5.2","5.3","5.4","6.0"],"symfony\/process":["2.7","2.8","3.4","4.0","4.1","4.2","4.3","4.4","5.0","5.1","5.2","5.3","5.4","6.0"],"symfony\/property-access":["2.7","2.8","3.4","4.0","4.1","4.2","4.3","4.4","5.0","5.1","5.2","5.3","5.4","6.0"],"symfony\/property-info":["2.8","3.4","4.0","4.1","4.2","4.3","4.4","5.0","5.1","5.2","5.3","5.4","6.0"],"symfony\/proxy-manager-bridge":["2.7","2.8","3.4","4.0","4.1","4.2","4.3","4.4","5.0","5.1","5.2","5.3","5.4","6.0"],"symfony\/rate-limiter":["5.2","5.3","5.4","6.0"],"symfony\/redis-messenger":["5.1","5.2","5.3","5.4","6.0"],"symfony\/rocket-chat-notifier":["5.1","5.2","5.3","5.4","6.0"],"symfony\/routing":["2.7","2.8","3.4","4.0","4.1","4.2","4.3","4.4","5.0","5.1","5.2","5.3","5.4","6.0"],"symfony\/runtime":["5.3","5.4","6.0"],"symfony\/security":["2.7","2.8","3.4","4.0","4.1","4.2","4.3","4.4"],"symfony\/security-bundle":["2.7","2.8","3.4","4.0","4.1","4.2","4.3","4.4","5.0","5.1","5.2","5.3","5.4","6.0"],"symfony\/security-core":["2.7","2.8","3.4","4.0","4.1","4.2","4.3","4.4","5.0","5.1","5.2","5.3","5.4","6.0"],"symfony\/security-csrf":["2.7","2.8","3.4","4.0","4.1","4.2","4.3","4.4","5.0","5.1","5.2","5.3","5.4","6.0"],"symfony\/security-guard":["2.8","3.4","4.0","4.1","4.2","4.3","4.4","5.0","5.1","5.2","5.3","5.4","6.0"],"symfony\/security-http":["2.7","2.8","3.4","4.0","4.1","4.2","4.3","4.4","5.0","5.1","5.2","5.3","5.4","6.0"],"symfony\/semaphore":["5.2","5.3","5.4","6.0"],"symfony\/sendgrid-mailer":["4.3","4.4","5.0","5.1","5.2","5.3","5.4","6.0"],"symfony\/sendinblue-mailer":["5.2","5.3","5.4","6.0"],"symfony\/sendinblue-notifier":["5.2","5.3","5.4","6.0"],"symfony\/serializer":["2.7","2.8","3.4","4.0","4.1","4.2","4.3","4.4","5.0","5.1","5.2","5.3","5.4","6.0"],"symfony\/sinch-notifier":["5.1","5.2","5.3","5.4","6.0"],"symfony\/slack-notifier":["5.0","5.1","5.2","5.3","5.4","6.0"],"symfony\/sms-biuras-notifier":["5.3","5.4","6.0"],"symfony\/smsapi-notifier":["5.2","5.3","5.4","6.0"],"symfony\/spot-hit-notifier":["5.3","5.4","6.0"],"symfony\/stopwatch":["2.7","2.8","3.4","4.0","4.1","4.2","4.3","4.4","5.0","5.1","5.2","5.3","5.4","6.0"],"symfony\/string":["5.0","5.1","5.2","5.3","5.4","6.0"],"symfony\/telegram-notifier":["5.0","5.1","5.2","5.3","5.4","6.0"],"symfony\/templating":["2.7","2.8","3.4","4.0","4.1","4.2","4.3","4.4","5.0","5.1","5.2","5.3","5.4","6.0"],"symfony\/translation":["2.7","2.8","3.4","4.0","4.1","4.2","4.3","4.4","5.0","5.1","5.2","5.3","5.4","6.0"],"symfony\/twig-bridge":["2.7","2.8","3.4","4.0","4.1","4.2","4.3","4.4","5.0","5.1","5.2","5.3","5.4","6.0"],"symfony\/twig-bundle":["2.7","2.8","3.4","4.0","4.1","4.2","4.3","4.4","5.0","5.1","5.2","5.3","5.4","6.0"],"symfony\/twilio-notifier":["5.0","5.1","5.2","5.3","5.4","6.0"],"symfony\/uid":["5.1","5.2","5.3","5.4","6.0"],"symfony\/validator":["2.7","2.8","3.4","4.0","4.1","4.2","4.3","4.4","5.0","5.1","5.2","5.3","5.4","6.0"],"symfony\/var-dumper":["2.7","2.8","3.4","4.0","4.1","4.2","4.3","4.4","5.0","5.1","5.2","5.3","5.4","6.0"],"symfony\/var-exporter":["4.2","4.3","4.4","5.0","5.1","5.2","5.3","5.4","6.0"],"symfony\/web-link":["3.4","4.0","4.1","4.2","4.3","4.4","5.0","5.1","5.2","5.3","5.4","6.0"],"symfony\/web-profiler-bundle":["2.7","2.8","3.4","4.0","4.1","4.2","4.3","4.4","5.0","5.1","5.2","5.3","5.4","6.0"],"symfony\/web-server-bundle":["3.4","4.0","4.1","4.2","4.3","4.4"],"symfony\/workflow":["3.4","4.0","4.1","4.2","4.3","4.4","5.0","5.1","5.2","5.3","5.4","6.0"],"symfony\/yaml":["2.7","2.8","3.4","4.0","4.1","4.2","4.3","4.4","5.0","5.1","5.2","5.3","5.4","6.0"],"symfony\/zulip-notifier":["5.2","5.3","5.4","6.0"]}},"headers":{"alt-svc":["h3-27=\":443\"; ma=86400, h3-28=\":443\"; ma=86400, h3-29=\":443\"; ma=86400, h3=\":443\"; ma=86400"],"content-encoding":["gzip"],"cf-ray":["66cca259cdb2dbd3-LHR"],"server":["cloudflare"],"nel":["{\"report_to\":\"cf-nel\",\"max_age\":604800}"],"report-to":["{\"endpoints\":[{\"url\":\"https:\\\/\\\/a.nel.cloudflare.com\\\/report\\\/v2?s=srccuYxsmKPqYIpvFwvhFayz34S2KwbSnP6aYUudeBhyulmXLn5lLbkdwx1KUX1pn1ql28s0QdcyASQRhCsIxvnabtuxKnqqV%2FqtelgIY3zFMaYq7EkG9bTrBRimzA%3D%3D\"}],\"group\":\"cf-nel\",\"max_age\":604800}"],"expect-ct":["max-age=604800, report-uri=\"https:\/\/report-uri.cloudflare.com\/cdn-cgi\/beacon\/expect-ct\""],"cf-cache-status":["DYNAMIC"],"x-symfony-router":["3hjnjz4dfxtohh4gibk6eanr7y"],"x-symfony-processor":["7zwai3z77ggmnxkao6dhwzsjxq"],"x-symfony-cluster":["egjbl6qhu5lse-master-7rqtwti"],"x-symfony-cache":["HIT"],"x-request-id":["3dvszhimcviaiakllz6ehlf3"],"x-debug-info":["eyJyZXRyaWVzIjowfQ=="],"vary":["Origin"],"strict-transport-security":["max-age=0"],"last-modified":["Mon, 31 May 2021 12:16:43 GMT"],"cache-control":["public,max-age=600,s-max-age=600,stale-if-error=60000"],"content-type":["application\/json"],"date":["Sat, 10 Jul 2021 20:45:10 GMT"]}}